respx/__init__.py
respx/__version__.py
respx/api.py
respx/fixtures.py
respx/handlers.py
respx/mocks.py
respx/models.py
respx/patterns.py
respx/plugin.py
respx/py.typed
respx/router.py
respx/transports.py
respx/types.py
respx/utils.py
respx-0.21.1.dist-info/LICENSE.md
respx-0.21.1.dist-info/METADATA
respx-0.21.1.dist-info/WHEEL
respx-0.21.1.dist-info/entry_points.txt
respx-0.21.1.dist-info/top_level.txt
respx-0.21.1.dist-info/RECORD
