Metadata-Version: 2.1
Name: respx
Version: 0.21.1
Summary: A utility for mocking out the Python HTTPX and HTTP Core libraries.
Home-page: https://lundberg.github.io/respx/
Author: Jonas Lundberg
Author-email: jonas@5monkeys.se
License: BSD-3-Clause
Project-URL: GitHub, https://github.com/lundberg/respx
Project-URL: Changelog, https://github.com/lundberg/respx/blob/master/CHANGELOG.md
Project-URL: Issues, https://github.com/lundberg/respx/issues
Keywords: httpx,httpcore,mock,responses,requests,async,http
Classifier: Development Status :: 5 - Production/Stable
Classifier: Intended Audience :: Developers
Classifier: License :: OSI Approved :: BSD License
Classifier: Operating System :: OS Independent
Classifier: Programming Language :: Python
Classifier: Programming Language :: Python :: 3
Classifier: Programming Language :: Python :: 3.7
Classifier: Programming Language :: Python :: 3.8
Classifier: Programming Language :: Python :: 3.9
Classifier: Programming Language :: Python :: 3.10
Classifier: Programming Language :: Python :: 3.11
Classifier: Programming Language :: Python :: 3.12
Requires-Python: >=3.7
License-File: LICENSE.md
